[{"id":"bones--pRRcSKZq","date":"2018-08-02T02:30:07.086Z","mediaFilename":"bones--pRRcSKZq.png","altText":"Dem bones dem bones dem – dry bones!","caption":"","postedToGit":true,"htmlFragment":"<li class=\"pane\">\n  <div class=\"time-stamp entry-meta\">\n    <a href=\"bones--pRRcSKZq.html\">\n      <time datetime=\"2018-08-02T02:30:07.086Z\">2018-8-1 22:30:07</time>\n    </a>\n  </div><img src=\"media/bones--pRRcSKZq.png\" alt=\"Dem bones dem bones dem – dry bones!\"></video><div class=\"media-caption entry-meta\"></div></li>","postedSingleVideoPage":true},{"id":"bones--RaCiBjwB","date":"2018-08-02T05:30:06.401Z","mediaFilename":"bones--RaCiBjwB.png","altText":"Dem bones dem bones dem – dry bones!","caption":"","postedToGit":true,"htmlFragment":"<li class=\"pane\">\n  <div class=\"time-stamp entry-meta\">\n    <a href=\"bones--RaCiBjwB.html\">\n      <time datetime=\"2018-08-02T05:30:06.401Z\">2018-8-2 01:30:06</time>\n    </a>\n  </div><img src=\"media/bones--RaCiBjwB.png\" alt=\"Dem bones dem bones dem – dry bones!\"></video><div class=\"media-caption entry-meta\"></div></li>","postedSingleVideoPage":true},{"id":"bones--cYTYLXRs","date":"2018-08-02T08:30:07.316Z","mediaFilename":"bones--cYTYLXRs.png","altText":"Dem bones dem bones dem – dry bones! Dem bones dem bones dem – extra bones!","caption":"Dem bones dem bones dem – extra bones!","postedToGit":true,"htmlFragment":"<li class=\"pane\">\n  <div class=\"time-stamp entry-meta\">\n    <a href=\"bones--cYTYLXRs.html\">\n      <time datetime=\"2018-08-02T08:30:07.316Z\">2018-8-2 04:30:07</time>\n    </a>\n  </div><img src=\"media/bones--cYTYLXRs.png\" alt=\"Dem bones dem bones dem – dry bones! Dem bones dem bones dem – extra bones!\"></video><div class=\"media-caption entry-meta\">Dem bones dem bones dem – extra bones!</div></li>","postedSingleVideoPage":true},{"id":"bones--PBngKsbm","date":"2018-08-02T11:30:07.925Z","mediaFilename":"bones--PBngKsbm.png","altText":"Dem bones dem bones dem – dry bones!","caption":"","postedToGit":true,"htmlFragment":"<li class=\"pane\">\n  <div class=\"time-stamp entry-meta\">\n    <a href=\"bones--PBngKsbm.html\">\n      <time datetime=\"2018-08-02T11:30:07.925Z\">2018-8-2 07:30:07</time>\n    </a>\n  </div><img src=\"media/bones--PBngKsbm.png\" alt=\"Dem bones dem bones dem – dry bones!\"></video><div class=\"media-caption entry-meta\"></div></li>","postedSingleVideoPage":true},{"id":"bones--bZGrFRuw","date":"2018-08-02T14:30:06.754Z","mediaFilename":"bones--bZGrFRuw.png","altText":"Dem bones dem bones dem – dry bones!","caption":"","postedToGit":true,"htmlFragment":"<li class=\"pane\">\n  <div class=\"time-stamp entry-meta\">\n    <a href=\"bones--bZGrFRuw.html\">\n      <time datetime=\"2018-08-02T14:30:06.754Z\">2018-8-2 10:30:06</time>\n    </a>\n  </div><img src=\"media/bones--bZGrFRuw.png\" alt=\"Dem bones dem bones dem – dry bones!\"></video><div class=\"media-caption entry-meta\"></div></li>","postedSingleVideoPage":true}]