[{"id":"bones--pRRcSKZq","date":"2018-08-02T02:30:07.086Z","mediaFilename":"bones--pRRcSKZq.png","altText":"Dem bones dem bones dem – dry bones!","caption":"","postedToGit":true,"htmlFragment":"<li class=\"pane\">\n  <div class=\"time-stamp entry-meta\">\n    <a href=\"bones--pRRcSKZq.html\">\n      <time datetime=\"2018-08-02T02:30:07.086Z\">2018-8-1 22:30:07</time>\n    </a>\n  </div><img src=\"media/bones--pRRcSKZq.png\" alt=\"Dem bones dem bones dem – dry bones!\"></video><div class=\"media-caption entry-meta\"></div></li>","postedSingleVideoPage":true},{"id":"bones--RaCiBjwB","date":"2018-08-02T05:30:06.401Z","mediaFilename":"bones--RaCiBjwB.png","altText":"Dem bones dem bones dem – dry bones!","caption":"","postedToGit":true,"htmlFragment":"<li class=\"pane\">\n  <div class=\"time-stamp entry-meta\">\n    <a href=\"bones--RaCiBjwB.html\">\n      <time datetime=\"2018-08-02T05:30:06.401Z\">2018-8-2 01:30:06</time>\n    </a>\n  </div><img src=\"media/bones--RaCiBjwB.png\" alt=\"Dem bones dem bones dem – dry bones!\"></video><div class=\"media-caption entry-meta\"></div></li>","postedSingleVideoPage":true},{"id":"bones--cYTYLXRs","date":"2018-08-02T08:30:07.316Z","mediaFilename":"bones--cYTYLXRs.png","altText":"Dem bones dem bones dem – dry bones! Dem bones dem bones dem – extra bones!","caption":"Dem bones dem bones dem – extra bones!","postedToGit":true,"htmlFragment":"<li class=\"pane\">\n  <div class=\"time-stamp entry-meta\">\n    <a href=\"bones--cYTYLXRs.html\">\n      <time datetime=\"2018-08-02T08:30:07.316Z\">2018-8-2 04:30:07</time>\n    </a>\n  </div><img src=\"media/bones--cYTYLXRs.png\" alt=\"Dem bones dem bones dem – dry bones! Dem bones dem bones dem – extra bones!\"></video><div class=\"media-caption entry-meta\">Dem bones dem bones dem – extra bones!</div></li>","postedSingleVideoPage":true},{"id":"bones--PBngKsbm","date":"2018-08-02T11:30:07.925Z","mediaFilename":"bones--PBngKsbm.png","altText":"Dem bones dem bones dem – dry bones!","caption":"","postedToGit":true,"htmlFragment":"<li class=\"pane\">\n  <div class=\"time-stamp entry-meta\">\n    <a href=\"bones--PBngKsbm.html\">\n      <time datetime=\"2018-08-02T11:30:07.925Z\">2018-8-2 07:30:07</time>\n    </a>\n  </div><img src=\"media/bones--PBngKsbm.png\" alt=\"Dem bones dem bones dem – dry bones!\"></video><div class=\"media-caption entry-meta\"></div></li>","postedSingleVideoPage":true},{"id":"bones--bZGrFRuw","date":"2018-08-02T14:30:06.754Z","mediaFilename":"bones--bZGrFRuw.png","altText":"Dem bones dem bones dem – dry bones!","caption":"","postedToGit":true,"htmlFragment":"<li class=\"pane\">\n  <div class=\"time-stamp entry-meta\">\n    <a href=\"bones--bZGrFRuw.html\">\n      <time datetime=\"2018-08-02T14:30:06.754Z\">2018-8-2 10:30:06</time>\n    </a>\n  </div><img src=\"media/bones--bZGrFRuw.png\" alt=\"Dem bones dem bones dem – dry bones!\"></video><div class=\"media-caption entry-meta\"></div></li>","postedSingleVideoPage":true},{"id":"bones--ucUckLrr","date":"2018-08-02T17:30:07.088Z","mediaFilename":"bones--ucUckLrr.png","altText":"Dem bones dem bones dem – dry bones!","caption":"","postedToGit":true,"htmlFragment":"<li class=\"pane\">\n  <div class=\"time-stamp entry-meta\">\n    <a href=\"bones--ucUckLrr.html\">\n      <time datetime=\"2018-08-02T17:30:07.088Z\">2018-8-2 13:30:07</time>\n    </a>\n  </div><img src=\"media/bones--ucUckLrr.png\" alt=\"Dem bones dem bones dem – dry bones!\"></video><div class=\"media-caption entry-meta\"></div></li>","postedSingleVideoPage":true},{"id":"bones--BfWeNILz","date":"2018-08-02T20:30:07.081Z","mediaFilename":"bones--BfWeNILz.png","altText":"Dem bones dem bones dem – dry bones!","caption":"","postedToGit":true,"htmlFragment":"<li class=\"pane\">\n  <div class=\"time-stamp entry-meta\">\n    <a href=\"bones--BfWeNILz.html\">\n      <time datetime=\"2018-08-02T20:30:07.081Z\">2018-8-2 16:30:07</time>\n    </a>\n  </div><img src=\"media/bones--BfWeNILz.png\" alt=\"Dem bones dem bones dem – dry bones!\"></video><div class=\"media-caption entry-meta\"></div></li>","postedSingleVideoPage":true},{"id":"bones--fnyXguGF","date":"2018-08-02T23:30:07.012Z","mediaFilename":"bones--fnyXguGF.png","altText":"Dem bones dem bones dem – dry bones!","caption":"","postedToGit":true,"htmlFragment":"<li class=\"pane\">\n  <div class=\"time-stamp entry-meta\">\n    <a href=\"bones--fnyXguGF.html\">\n      <time datetime=\"2018-08-02T23:30:07.012Z\">2018-8-2 19:30:07</time>\n    </a>\n  </div><img src=\"media/bones--fnyXguGF.png\" alt=\"Dem bones dem bones dem – dry bones!\"></video><div class=\"media-caption entry-meta\"></div></li>","postedSingleVideoPage":true},{"id":"bones--CtvwLNfL","date":"2018-08-03T02:30:06.796Z","mediaFilename":"bones--CtvwLNfL.png","altText":"Dem bones dem bones dem – dry bones!","caption":"","postedToGit":true,"htmlFragment":"<li class=\"pane\">\n  <div class=\"time-stamp entry-meta\">\n    <a href=\"bones--CtvwLNfL.html\">\n      <time datetime=\"2018-08-03T02:30:06.796Z\">2018-8-2 22:30:06</time>\n    </a>\n  </div><img src=\"media/bones--CtvwLNfL.png\" alt=\"Dem bones dem bones dem – dry bones!\"></video><div class=\"media-caption entry-meta\"></div></li>","postedSingleVideoPage":true},{"id":"bones--FzSCsWus","date":"2018-08-03T05:30:06.865Z","mediaFilename":"bones--FzSCsWus.png","altText":"Dem bones dem bones dem – dry bones!","caption":"","postedToGit":true,"htmlFragment":"<li class=\"pane\">\n  <div class=\"time-stamp entry-meta\">\n    <a href=\"bones--FzSCsWus.html\">\n      <time datetime=\"2018-08-03T05:30:06.865Z\">2018-8-3 01:30:06</time>\n    </a>\n  </div><img src=\"media/bones--FzSCsWus.png\" alt=\"Dem bones dem bones dem – dry bones!\"></video><div class=\"media-caption entry-meta\"></div></li>","postedSingleVideoPage":true}]